{"department": "信息学院", "name": "陈红", "major": ["大数据", "隐私保护", "新硬件"], "url": "http://info.ruc.edu.cn/academic_professor.php?teacher_id=56", "homepage": "http://bi.ruc.edu.cn/chen/index.html", "position": ["教授"]}
{"department": "信息学院", "name": "陈文萍", "major": ["传感器网络"], "url": "http://info.ruc.edu.cn/academic_professor.php?teacher_id=43", "email": "wpchen@vis.cs.tsinghua.edu.cn", "position": ["讲师"]}
{"department": "信息学院", "name": "陈晋川", "major": ["区块链", "分布式"], "url": "http://info.ruc.edu.cn/academic_professor.php?teacher_id=22", "homepage": "http://iir.ruc.edu.cn/%7Ejchchen/", "email": "jcchen@ruc.edu.cn", "position": ["副教授"]}
{"department": "信息学院", "name": "柴云鹏", "major": ["新硬件系统优化", "分布式", "大数据分析", "云计算资源管理"], "url": "http://info.ruc.edu.cn/academic_professor.php?teacher_id=42", "phone": "010-82504345", "email": "ypchai@ruc.edu.cn", "position": ["副教授"]}
{"department": "信息学院", "name": "韩家炜", "major": ["数据挖掘"], "url": "http://info.ruc.edu.cn/academic_professor.php?teacher_id=142", "homepage": "http://www.cs.uiuc.edu/homes/hanj/", "position": ["客座教授"]}
{"department": "信息学院", "name": "Ramamohanarao Kotagiri", "major": ["知识发现", "数据挖掘"], "url": "http://info.ruc.edu.cn/academic_professor.php?teacher_id=140", "position": ["客座教授"]}
{"department": "信息学院", "name": "Christian Jensen", "major": ["数据管理", "数据密集型系统"], "url": "http://info.ruc.edu.cn/academic_professor.php?teacher_id=139", "email": "无", "position": ["客座教授"]}
{"department": "信息学院", "name": "曹巍", "major": ["数据库", "自调优自管理", "数据管理"], "url": "http://info.ruc.edu.cn/academic_professor.php?teacher_id=41", "position": ["讲师"]}
{"department": "信息学院", "name": "Calton Pu", "major": ["分布式", "数据管理", "操作系统"], "url": "http://info.ruc.edu.cn/academic_professor.php?teacher_id=138", "position": ["客座教授"]}
{"department": "信息学院", "name": "付虹蛟", "major": ["信息系统", "信息伦理"], "url": "http://info.ruc.edu.cn/academic_professor.php?teacher_id=66", "phone": "010-82500903", "position": ["副教授"]}
{"department": "信息学院", "name": "范举", "major": ["大数据分析"], "url": "http://info.ruc.edu.cn/academic_professor.php?teacher_id=162", "phone": "+86-10-62514562", "homepage": "http://iir.ruc.edu.cn/~fanj/", "email": "fanj@ruc.edu.cn", "position": ["副教授"]}
{"department": "信息学院", "name": "杜小勇", "major": ["信息检索", "语义网", "数据管理"], "url": "http://info.ruc.edu.cn/academic_professor.php?teacher_id=57", "phone": "86-10-6251 5259", "position": ["教授"]}
{"department": "信息学院", "name": "杜玮", "major": ["社会网络", "推荐系统", "科研计量学", "智慧健康", "知识图谱", "大数据"], "url": "http://info.ruc.edu.cn/academic_professor.php?teacher_id=166", "phone": "010-82500903", "email": "ahduwei@ruc.edu.cn", "position": ["讲师"]}
{"department": "信息学院", "name": "堵丁柱", "major": ["计算机网络", "计算理论", "组合优化"], "url": "http://info.ruc.edu.cn/academic_professor.php?teacher_id=141", "position": ["客座教授"]}
{"department": "信息学院", "name": "李德英", "major": ["社会网络", "数据网络", "图论", "物联网"], "url": "http://info.ruc.edu.cn/academic_professor.php?teacher_id=60", "phone": "62519223", "email": "deyingli@ruc.edu.cn", "position": ["教授"]}
{"department": "信息学院", "name": "李翠平", "major": ["数据库", "大数据分析", "深度学习", "图表示学习"], "url": "http://info.ruc.edu.cn/academic_professor.php?teacher_id=59", "phone": "010-62516243", "email": "licuiping@ruc.edu.cn", "position": ["教授"]}
{"department": "信息学院", "name": "金琴", "major": ["多媒体数据内容分析", "人机交互"], "url": "http://info.ruc.edu.cn/academic_professor.php?teacher_id=26", "phone": "010-62510042", "homepage": "www.jin-qin.com", "email": "qjin@ruc.edu.cn", "position": ["副教授"]}
{"department": "信息学院", "name": "蒋洪迅", "major": ["运筹优化", "机器学习", "推荐系统", "网络金融", "大数据分析", "数据挖掘"], "url": "http://info.ruc.edu.cn/academic_professor.php?teacher_id=67", "phone": "86-01-82500904", "homepage": "http://info.ruc.edu.cn/academic_professor.php?teacher_id=67", "email": "jianghx@ruc.edu.cn", "position": ["副教授"]}
{"department": "信息学院", "name": "胡鹤", "major": ["语义网", "人工智能"], "url": "http://info.ruc.edu.cn/academic_professor.php?teacher_id=25", "email": "hehu AT ruc.edu.cn", "position": ["副教授"]}
{"department": "信息学院", "name": "黄铭钧", "major": ["大数据分析", "索引技术", "数据库性能", "空间数据库", "云计算"], "url": "http://info.ruc.edu.cn/academic_professor.php?teacher_id=143", "position": ["客座教授"]}
{"department": "信息学院", "name": "黄建军", "major": ["应用分析", "程序分析", "软件安全性"], "url": "http://info.ruc.edu.cn/academic_professor.php?teacher_id=167", "phone": "82500902", "homepage": "https://hjjandy.github.io/", "email": "HJJ@ruc.edu.cn", "position": ["讲师"]}
{"department": "信息学院", "name": "何军", "major": ["数据管理", "商务智能", "机器学习", "数据挖掘"], "url": "http://info.ruc.edu.cn/academic_professor.php?teacher_id=58", "phone": "010-62514014", "homepage": "http://iir.ruc.edu.cn/~hejun/", "email": "hejun[at]ruc.edu.cn", "position": ["教授"]}
{"department": "信息学院", "name": "刘桃", "major": ["声图文多模态信息处理", "听音辨貌"], "url": "http://info.ruc.edu.cn/academic_professor.php?teacher_id=46", "email": "tliu@ruc.edu.cn", "position": ["副教授"]}
{"department": "信息学院", "name": "刘青", "major": ["生物信息学", "云计算", "数据管理", "机器学习"], "url": "http://info.ruc.edu.cn/academic_professor.php?teacher_id=28", "phone": "010 - 82500901", "email": "qliu@ruc.edu.cn", "position": ["副教授"]}
{"department": "信息学院", "name": "刘伶", "major": ["分布式计算", "数据管理", "信息安全"], "url": "http://info.ruc.edu.cn/academic_professor.php?teacher_id=144", "position": ["客座教授"]}
{"department": "信息学院", "name": "李锡荣", "major": ["跨媒体表示学习", "图像自然语言理解", "图像视频搜索"], "url": "http://info.ruc.edu.cn/academic_professor.php?teacher_id=44", "homepage": "http://lixirong.net/", "email": "名下划线姓@126.com", "position": ["副教授"]}
{"department": "信息学院", "name": "梁彬", "major": ["软件安全性"], "url": "http://info.ruc.edu.cn/academic_professor.php?teacher_id=27", "phone": "010-62512492", "email": "liangb(at)ruc(dot)edu(dot)cn", "position": ["教授"]}
{"department": "信息学院", "name": "李亚平", "major": ["移动通信技术"], "url": "http://info.ruc.edu.cn/academic_professor.php?teacher_id=45", "email": "liyp@ruc.edu.cn", "position": ["讲师"]}
{"department": "信息学院", "name": "梁循", "major": ["机器学习", "金融模型", "知识图谱", "网络金融", "社会计算", "自然语言处理"], "url": "http://info.ruc.edu.cn/academic_professor.php?teacher_id=79", "email": "xunliangruc@163.com (ruc, Renmin University of China)", "position": ["教授"]}
{"department": "信息学院", "name": "李倩", "major": ["企业资源规划", "信息系统使用行为"], "url": "http://info.ruc.edu.cn/academic_professor.php?teacher_id=75", "phone": "(8610) 82500906", "email": "linda_lq@ruc.edu.cn", "position": ["副教授"]}
{"department": "信息学院", "name": "石文昌", "major": ["系统软件", "数字取证", "信息安全", "可信计算"], "url": "http://info.ruc.edu.cn/academic_professor.php?teacher_id=63", "phone": "010-62511279", "homepage": "http://iser.ruc.edu.cn/wshi", "email": "wenchang_at_ruc_edu_cn", "position": ["教授"]}
{"department": "信息学院", "name": "陆嘉恒", "major": ["空间数据库", "数据管理", "文本数据管理", "云计算", "大数据"], "url": "http://info.ruc.edu.cn/academic_professor.php?teacher_id=61", "phone": "01062515142", "homepage": "http://datasearch.ruc.edu.cn", "email": "jiahenglu@gmail.com", "position": ["教授"]}
{"department": "信息学院", "name": "秦波", "major": ["应用密码学", "信息安全", "云计算安全", "数据安全", "隐私保护"], "url": "http://info.ruc.edu.cn/academic_professor.php?teacher_id=47", "phone": "010-62512492, 13552253617", "email": "bo.qin@ruc.edu.cn", "position": ["副教授"]}
{"department": "信息学院", "name": "孟小峰", "major": ["面向新硬件的数据库技术"], "url": "http://info.ruc.edu.cn/academic_professor.php?teacher_id=62", "phone": "86-10-62512719", "homepage": "http://idke.ruc.edu.cn/", "email": "xfmeng@ruc.edu.cn", "position": ["教授"]}
{"department": "信息学院", "name": "卢志武", "major": ["自监督学习", "元学习", "机器学习", "领域迁移", "小样本学习", "半监督学习"], "url": "http://info.ruc.edu.cn/academic_professor.php?teacher_id=30", "email": "luzhiwu[AT]ruc.edu.cn", "position": ["教授"]}
{"department": "信息学院", "name": "苏俊", "major": ["数据库", "计算机应用开发与系统集成", "电子商务电子政务", ""], "url": "http://info.ruc.edu.cn/academic_professor.php?teacher_id=68", "position": ["副教授"]}
{"department": "信息学院", "name": "孟卫一", "major": ["搜索引擎", "元搜索引擎", "万维网", "数据库集成"], "url": "http://info.ruc.edu.cn/academic_professor.php?teacher_id=145", "position": ["客座教授"]}
{"department": "信息学院", "name": "卢卫", "major": ["云计算", "数据管理", "索引", "空间数据库", "文本数据库"], "url": "http://info.ruc.edu.cn/academic_professor.php?teacher_id=29", "homepage": "http://iir.ruc.edu.cn/~luwei", "email": "uqwlu@ruc.edu.cn", "position": ["副教授"]}
{"department": "信息学院", "name": "王明明", "major": ["信息生产力战略研究", "信息经济与信息管理", "信息化与城镇化"], "url": "http://info.ruc.edu.cn/academic_professor.php?teacher_id=70", "phone": "82500903", "email": "mingmwang@263.net", "position": ["副教授"]}
{"department": "信息学院", "name": "王良", "major": ["系统软件", "数据库", "智能科学", "软件工程"], "url": "http://info.ruc.edu.cn/academic_professor.php?teacher_id=32", "phone": "010-62514510", "email": "wangliang@ruc.edu.cn", "position": ["副教授"]}
{"department": "信息学院", "name": "孙彩虹", "major": ["复杂系统建模", "基于主体的计算经济学", "社会网络"], "url": "http://info.ruc.edu.cn/academic_professor.php?teacher_id=69", "phone": "86-10-82500906", "email": "chsun@ruc.edu.cn", "position": ["副教授"]}
{"department": "信息学院", "name": "王秋月", "major": ["信息检索", "数据库", "大规模知识库", "自然语言问答"], "url": "http://info.ruc.edu.cn/academic_professor.php?teacher_id=51", "phone": "010-62514406", "homepage": "http://202.112.113.2/wangqiuyue", "email": "qiuyuew@ruc.edu.cn", "position": ["讲师"]}
{"department": "信息学院", "name": "王璞巍", "major": ["区块链", "服务计算"], "url": "http://info.ruc.edu.cn/academic_professor.php?teacher_id=50", "email": "wangpuwei[at]ruc.edu.cn", "position": ["副教授"]}
{"department": "信息学院", "name": "孙辉", "major": ["高性能数据库", "大数据分析"], "url": "http://info.ruc.edu.cn/academic_professor.php?teacher_id=48", "email": "sun_h@ruc.edu.cn", "position": ["副教授"]}
{"department": "信息学院", "name": "覃雄派", "major": ["大数据分析", "高性能数据库", "并行计算"], "url": "http://info.ruc.edu.cn/academic_professor.php?teacher_id=49", "email": "xiongpai@sohu.com, qxp1990@sina.com", "position": ["副教授"]}
{"department": "信息学院", "name": "覃飙", "major": ["深度学习", "大规模图数据库", "时间序列分析", "大数据分析"], "url": "http://info.ruc.edu.cn/academic_professor.php?teacher_id=31", "email": "qinbiao@ruc.edu.cn", "position": ["副教授"]}
{"department": "信息学院", "name": "许洁萍", "major": ["视频信息检索", "多媒体信号处理", "多媒体内容分析与检索", "音乐计算模型分析"], "url": "http://info.ruc.edu.cn/academic_professor.php?teacher_id=34", "phone": "82500902", "email": "xjieping@ruc.edu.cn", "position": ["副教授"]}
{"department": "信息学院", "name": "许伟", "major": ["商业分析", "智能社会治理", "量化分析", "区块链", "金融科技"], "url": "http://info.ruc.edu.cn/academic_professor.php?teacher_id=71", "phone": "010-82500904", "homepage": "lisa.ruc.edu.cn", "email": "weixu@ruc.edu.cn", "position": ["副教授"]}
{"department": "信息学院", "name": "徐君", "major": ["搜索引擎", "大数据分析", "信息检索", "机器学习"], "url": "http://info.ruc.edu.cn/academic_professor.php?teacher_id=169", "homepage": "https://scholar.google.com/citations?user=su14mcEAAAAJ", "email": "junxu [AT] ruc.edu.cn", "position": ["教授"]}
{"department": "信息学院", "name": "谢红", "major": ["计算机应用"], "url": "http://info.ruc.edu.cn/academic_professor.php?teacher_id=53", "email": "hongx@ruc.edu.cn", "position": ["讲师"]}
{"department": "信息学院", "name": "肖林", "url": "http://info.ruc.edu.cn/academic_professor.php?teacher_id=52", "position": ["讲师"]}
{"department": "信息学院", "name": "文继荣", "major": ["机器学习", "信息检索", "数据管理", "数据挖掘"], "url": "http://info.ruc.edu.cn/academic_professor.php?teacher_id=64", "phone": "010-85203315", "email": "jirong.wen@gmail.com, jrwen@ruc.edu.cn", "position": ["教授"]}
{"department": "信息学院", "name": "魏哲巍", "major": ["数据库", "图表示学习与图神经网络", "图算法"], "url": "http://info.ruc.edu.cn/academic_professor.php?teacher_id=33", "homepage": "www.weizhewei.com", "email": "zhewei at ruc.edu.cn", "position": ["教授"]}
{"department": "信息学院", "name": "王珊", "major": ["数据库", "内存数据库", "高性能数据库"], "url": "http://info.ruc.edu.cn/academic_professor.php?teacher_id=150", "phone": "86-10-62515128", "homepage": "http://www.ccf-dbs.org.cn/wangshan", "email": "swang@ruc.edu.cn", "position": ["教授"]}
{"department": "信息学院", "name": "杨刚", "major": ["群智能", "深度学习", "演化计算", "零样本学习"], "url": "http://info.ruc.edu.cn/academic_professor.php?teacher_id=54", "phone": "82500902", "email": "yanggang@ruc.edu.cn", "position": ["副教授"]}
{"department": "信息学院", "name": "余力", "major": ["个性化推荐系统", "大数据分析", "金融科技与数据分析"], "url": "http://info.ruc.edu.cn/academic_professor.php?teacher_id=73", "phone": "86-10-82500907", "email": "buaayuli@ruc.edu.cn", "position": ["副教授"]}
{"department": "信息学院", "name": "于旭", "major": ["图数据库", "关键词搜索"], "url": "http://info.ruc.edu.cn/academic_professor.php?teacher_id=147", "position": ["客座教授"]}
{"department": "信息学院", "name": "游伟", "major": ["移动安全", "安全漏洞挖掘", "恶意程序分析"], "url": "http://info.ruc.edu.cn/academic_professor.php?teacher_id=171", "phone": "010-62514510", "homepage": "http://www.youwei.name", "email": "youwei@ruc.edu.cn", "position": ["副教授"]}
{"department": "信息学院", "name": "尤晓东", "major": ["域名系统", "计算机基础教育", "互联网应用"], "url": "http://info.ruc.edu.cn/academic_professor.php?teacher_id=130", "position": ["副教授"]}
{"department": "信息学院", "name": "杨小平", "major": ["电子政务", "信息系统工程", "网络安全技术"], "url": "http://info.ruc.edu.cn/academic_professor.php?teacher_id=80", "phone": "62511127", "email": "yang@ruc.edu.cn", "position": ["教授"]}
{"department": "信息学院", "name": "杨楠", "major": ["社会网络分析", "机器学习", "社区发现", "社会计算", "数据挖掘"], "url": "http://info.ruc.edu.cn/academic_professor.php?teacher_id=35", "phone": "010-82500902", "email": "yangnan@ruc.edu.cn", "position": ["副教授"]}
{"department": "信息学院", "name": "杨波", "major": ["电子商务", "治理", "外包"], "url": "http://info.ruc.edu.cn/academic_professor.php?teacher_id=72", "email": "yangbo@ruc.edu.cn, yangbo_ruc@126.com", "position": ["副教授"]}
{"department": "信息学院", "name": "战疆", "major": ["大数据分析", "数据挖掘", "数据库", "信息检索", "数据恢复"], "url": "http://info.ruc.edu.cn/academic_professor.php?teacher_id=131", "position": ["副教授"]}
{"department": "信息学院", "name": "张孝", "major": ["大数据获取", "非结构化数据管理", "应用技术", "数据库体系结构"], "url": "http://info.ruc.edu.cn/academic_professor.php?teacher_id=36", "phone": "86-10-62511524(o)", "email": "zhangxiao@ruc.edu.cn", "position": ["教授"]}
{"department": "信息学院", "name": "张文平", "major": ["商业数据分析", "观点挖掘与情感分析", "机器学习", "文本挖掘", "大数据分析", "主题模型"], "url": "http://info.ruc.edu.cn/academic_professor.php?teacher_id=164", "email": "wpzhang@ruc.edu.cn", "position": ["讲师"]}
{"department": "信息学院", "name": "张立峰", "major": ["遗传算法与优化", "非线性系统辨识与预测", "智能建模"], "url": "http://info.ruc.edu.cn/academic_professor.php?teacher_id=77", "position": ["讲师"]}
{"department": "信息学院", "name": "张静", "major": ["深度学习", "强化学习", "知识图谱", "社会网络", "机器学习"], "url": "http://info.ruc.edu.cn/academic_professor.php?teacher_id=163", "homepage": "https://xiaojingzi.github.io/", "email": "zhang-jing@ruc.edu.cn", "position": ["讲师"]}
{"department": "信息学院", "name": "张金玲", "major": ["网络安全", "虚拟现实", "多媒体"], "url": "http://info.ruc.edu.cn/academic_professor.php?teacher_id=132", "position": ["副教授"]}
{"department": "信息学院", "name": "张成奇", "major": ["人工智能", "数据挖掘"], "url": "http://info.ruc.edu.cn/academic_professor.php?teacher_id=148", "position": ["客座教授"]}
{"department": "信息学院", "name": "余艳", "major": ["智慧医养", "知识管理", "数字创新"], "url": "http://info.ruc.edu.cn/academic_professor.php?teacher_id=76", "email": "yanyu@ruc.edu.cn", "position": ["副教授"]}
{"department": "信息学院", "name": "周晓方", "major": ["多媒体", "数据库"], "url": "http://info.ruc.edu.cn/academic_professor.php?teacher_id=149", "position": ["客座教授"]}
{"department": "信息学院", "name": "周春来", "major": ["隐私保护", "深度学习"], "url": "http://info.ruc.edu.cn/academic_professor.php?teacher_id=38", "phone": "010-62512492", "email": "czhou # ruc # edu # cn", "position": ["副教授"]}
{"department": "信息学院", "name": "钟佳桂", "major": ["电子商务信任", "信息管理", "在线信任"], "url": "http://info.ruc.edu.cn/academic_professor.php?teacher_id=78", "email": "zhongjg@ruc.edu.cn", "position": ["讲师"]}
{"department": "信息学院", "name": "赵素云", "major": ["增量学习", "不确定信息处理", "机器学习", "隐私保护"], "url": "http://info.ruc.edu.cn/academic_professor.php?teacher_id=37", "phone": "010-62514034", "email": "zhao.suyun@yahoo.com; zhaosuyun@ruc.edu.cn", "position": ["副教授"]}
{"department": "信息学院", "name": "张延松", "major": ["面向新硬件的数据库技术", "内存数据库"], "url": "http://info.ruc.edu.cn/academic_professor.php?teacher_id=165", "email": "zhangys_ruc@hotmail.com", "position": ["副教授"]}
{"department": "信息学院", "name": "张新勇", "major": ["触控交互", "视线交互", "体感交互", "人机交互"], "url": "http://info.ruc.edu.cn/academic_professor.php?teacher_id=74", "email": "x.y.zhang@(RUC邮箱地址)", "position": ["副教授"]}
{"department": "信息学院", "name": "窦志成", "major": ["信息抽取", "机器学习", "大数据", "信息检索", "自然语言处理", "数据挖掘"], "url": "http://info.ruc.edu.cn/academic_professor.php?teacher_id=24", "homepage": "http://playbigdata.ruc.edu.cn/dou/", "email": "dou at ruc.edu.cn", "position": ["教授"]}
{"department": "信息学院", "name": "赵鑫", "major": ["数据挖掘", "推荐系统", "人工智能", "自然语言处理"], "url": "http://info.ruc.edu.cn/academic_professor.php?teacher_id=55", "homepage": "http://aibox.ruc.edu.cn/", "email": "batmanfly@gmail.com; batmanfly@qq.com; batmanfly@ruc.edu.cn", "position": ["副教授"]}
{"department": "信息学院", "name": "陈跃国", "major": ["可视化分析", "知识图谱", "金融量化分析"], "url": "http://info.ruc.edu.cn/academic_professor.php?teacher_id=23", "email": "chenyueguo@ruc.edu.cn", "position": ["教授"]}
{"department": "信息学院", "name": "朱青", "major": ["可信服务计算", "分布式系统", "云计算", "大数据", "自然语言处理"], "url": "http://info.ruc.edu.cn/academic_professor.php?teacher_id=40", "phone": "(010)62511524", "email": "zq@ruc.edu.cn", "position": ["教授"]}
{"department": "信息学院", "name": "陈熙霖", "major": ["计算机视觉", "图像处理", "模式识别"], "url": "http://info.ruc.edu.cn/academic_professor.php?teacher_id=133", "position": ["兼职教授"]}
{"department": "信息学院", "name": "左美云", "major": ["知识图谱", "区块链", "健康医疗养老大数据分析与应用"], "url": "http://info.ruc.edu.cn/academic_professor.php?teacher_id=81", "phone": "010-62511569", "email": "zuomy@ruc.edu.cn", "position": ["教授"]}
{"department": "信息学院", "name": "刘家俊", "major": ["社会计算", "多媒体", "人工智能", "机器学习"], "url": "http://info.ruc.edu.cn/academic_professor.php?teacher_id=161", "homepage": "https://sites.google.com/site/drjiajunliu/homepage", "email": "jiajunliu AT ruc DOT edu DOT cn", "position": ["副教授"]}
{"department": "信息学院", "name": "张峰", "major": ["异构数据库", "高性能计算", "大数据"], "url": "http://info.ruc.edu.cn/academic_professor.php?teacher_id=170", "phone": "01062514406", "homepage": "https://fengzhangcs.github.io/", "email": "fengzhang@ruc.edu.cn", "position": ["讲师"]}
{"department": "信息学院", "name": "叶向", "major": ["计算机基础教育", "计算机应用", "运筹学"], "url": "http://info.ruc.edu.cn/academic_professor.php?teacher_id=129", "phone": "010-82500686", "email": "yexiang@ruc.edu.cn", "position": ["副教授"]}
{"department": "信息学院", "name": "闫俐", "major": ["计算机基础教育", "计算机应用"], "url": "http://info.ruc.edu.cn/academic_professor.php?teacher_id=128", "phone": "010-82500686", "position": ["副教授"]}
{"department": "信息学院", "name": "王永才", "major": ["计算机视觉", "物联网中群智感知与优化方法", "社交网络中影响力最大化研究"], "url": "http://info.ruc.edu.cn/academic_professor.php?teacher_id=160", "phone": "010-82500901", "homepage": "http://in.ruc.edu.cn", "email": "ycw@ruc.edu.cn", "position": ["副教授"]}
{"department": "信息学院", "name": "程絮森", "major": ["大数据与行为", "虚拟团队与人机协作", "共享经济网约车"], "url": "http://info.ruc.edu.cn/academic_professor.php?teacher_id=172", "phone": "010-62513624", "email": "xusen.cheng@ruc.edu.cn", "position": ["教授"]}
